LICENSE.txt
MANIFEST.in
README.rst
setup.py
doc/ttyrec/ttyrecgenerator_howto_en.gif
doc/ttyrec/ttyrecgenerator_howto_es.gif
locale/es.po
man/es/man1/ttyrecgenerator.1
man/man1/ttyrecgenerator.1
ttyrecgenerator/__init__.py
ttyrecgenerator/cmd_ttyrecgenerator.py
ttyrecgenerator/libttyrecgenerator.py
ttyrecgenerator.egg-info/PKG-INFO
ttyrecgenerator.egg-info/SOURCES.txt
ttyrecgenerator.egg-info/dependency_links.txt
ttyrecgenerator.egg-info/entry_points.txt
ttyrecgenerator.egg-info/not-zip-safe
ttyrecgenerator.egg-info/requires.txt
ttyrecgenerator.egg-info/top_level.txt
ttyrecgenerator/locale/es/LC_MESSAGES/ttyrecgenerator.mo