Metadata-Version: 2.1
Name: ttyrecgenerator
Version: 0.6.0
Summary: Python module to save console output into a GIF or a video
Home-page: https://ttyrecgenerator.sourceforge.io/
Author: Turulomio
Author-email: turulomio@yahoo.es
License: GPL-3
Keywords: ttyrec save console output
Platform: UNKNOWN
Classifier: Development Status :: 4 - Beta
Classifier: Intended Audience :: Developers
Classifier: Topic :: Software Development :: Build Tools
Classifier: License :: OSI Approved :: GNU General Public License v3 (GPLv3)
Classifier: Programming Language :: Python :: 3
